[
  {
    "name": "Player",
    "chips": 12000,
    "wins": 1,
    "room": "normal"
  },
  {
    "name": "Player",
    "chips": 2550,
    "wins": 3,
    "room": "normal"
  },
  {
    "name": "Player",
    "chips": 2200,
    "wins": 2,
    "room": "normal"
  },
  {
    "name": "Player",
    "chips": 2000,
    "wins": 0,
    "room": "normal"
  },
  {
    "name": "Player",
    "chips": 1950,
    "wins": 0,
    "room": "normal"
  },
  {
    "name": "玩家",
    "chips": 1875,
    "wins": 0,
    "room": "normal"
  },
  {
    "name": "Player",
    "chips": 1755,
    "wins": 0,
    "room": "normal"
  },
  {
    "name": "Player",
    "chips": 263,
    "wins": 0,
    "room": "normal"
  }
]